odoo/addons/l10n_br_nfse_paulistana/README.rst
odoo/addons/l10n_br_nfse_paulistana/__init__.py
odoo/addons/l10n_br_nfse_paulistana/__manifest__.py
odoo/addons/l10n_br_nfse_paulistana/constants/paulistana.py
odoo/addons/l10n_br_nfse_paulistana/i18n/l10n_br_nfse_paulistana.pot
odoo/addons/l10n_br_nfse_paulistana/i18n/pt_BR.po
odoo/addons/l10n_br_nfse_paulistana/models/__init__.py
odoo/addons/l10n_br_nfse_paulistana/models/document.py
odoo/addons/l10n_br_nfse_paulistana/models/res_company.py
odoo/addons/l10n_br_nfse_paulistana/readme/CONFIGURE.rst
odoo/addons/l10n_br_nfse_paulistana/readme/CONTRIBUTORS.rst
odoo/addons/l10n_br_nfse_paulistana/readme/DESCRIPTION.rst
odoo/addons/l10n_br_nfse_paulistana/readme/INSTALL.rst
odoo/addons/l10n_br_nfse_paulistana/readme/ROADMAP.rst
odoo/addons/l10n_br_nfse_paulistana/readme/USAGE.rst
odoo/addons/l10n_br_nfse_paulistana/static/description/icon.png
odoo/addons/l10n_br_nfse_paulistana/static/description/index.html
odoo/addons/l10n_br_nfse_paulistana/tests/__init__.py
odoo/addons/l10n_br_nfse_paulistana/tests/test_fiscal_document_nfse_paulistana.py
odoo/addons/l10n_br_nfse_paulistana/tests/nfse/paulistana.xml
odoo_addon_l10n_br_nfse_paulistana-15.0.1.1.0.dist-info/METADATA
odoo_addon_l10n_br_nfse_paulistana-15.0.1.1.0.dist-info/WHEEL
odoo_addon_l10n_br_nfse_paulistana-15.0.1.1.0.dist-info/top_level.txt
odoo_addon_l10n_br_nfse_paulistana-15.0.1.1.0.dist-info/RECORD
