Metadata-Version: 2.1
Name: odoo-addon-l10n_br_nfse_paulistana
Version: 15.0.1.1.0
Summary: NFS-e (Nota Paulistana)
Home-page: https://github.com/OCA/l10n-brazil
Author: KMEE, Odoo Community Association (OCA)
Author-email: support@odoo-community.org
License: AGPL-3
Classifier: Programming Language :: Python
Classifier: Framework :: Odoo
Classifier: Framework :: Odoo :: 15.0
Classifier: License :: OSI Approved :: GNU Affero General Public License v3
Classifier: Development Status :: 4 - Beta
Requires-Python: >=3.8
Requires-Dist: erpbrasil.assinatura
Requires-Dist: erpbrasil.base
Requires-Dist: erpbrasil.edoc>=2.5.2
Requires-Dist: erpbrasil.transmissao>=1.1.0
Requires-Dist: nfselib.paulistana
Requires-Dist: odoo-addon-l10n-br-nfse<15.1dev,>=15.0dev
Requires-Dist: odoo<15.1dev,>=15.0a
Requires-Dist: unidecode
